MANIFEST.in
README.md
setup.cfg
setup.py
setup_support.py
/home/oskar/secp256k1-py/libsecp256k1/.gitignore
/home/oskar/secp256k1-py/libsecp256k1/.travis.yml
/home/oskar/secp256k1-py/libsecp256k1/COPYING
/home/oskar/secp256k1-py/libsecp256k1/Makefile.am
/home/oskar/secp256k1-py/libsecp256k1/Makefile.in
/home/oskar/secp256k1-py/libsecp256k1/README.md
/home/oskar/secp256k1-py/libsecp256k1/TODO
/home/oskar/secp256k1-py/libsecp256k1/aclocal.m4
/home/oskar/secp256k1-py/libsecp256k1/autogen.sh
/home/oskar/secp256k1-py/libsecp256k1/configure
/home/oskar/secp256k1-py/libsecp256k1/configure.ac
/home/oskar/secp256k1-py/libsecp256k1/libsecp256k1.pc.in
/home/oskar/secp256k1-py/libsecp256k1/autom4te.cache/output.0
/home/oskar/secp256k1-py/libsecp256k1/autom4te.cache/output.1
/home/oskar/secp256k1-py/libsecp256k1/autom4te.cache/output.2
/home/oskar/secp256k1-py/libsecp256k1/autom4te.cache/requests
/home/oskar/secp256k1-py/libsecp256k1/autom4te.cache/traces.0
/home/oskar/secp256k1-py/libsecp256k1/autom4te.cache/traces.1
/home/oskar/secp256k1-py/libsecp256k1/autom4te.cache/traces.2
/home/oskar/secp256k1-py/libsecp256k1/build-aux/compile
/home/oskar/secp256k1-py/libsecp256k1/build-aux/config.guess
/home/oskar/secp256k1-py/libsecp256k1/build-aux/config.sub
/home/oskar/secp256k1-py/libsecp256k1/build-aux/depcomp
/home/oskar/secp256k1-py/libsecp256k1/build-aux/install-sh
/home/oskar/secp256k1-py/libsecp256k1/build-aux/ltmain.sh
/home/oskar/secp256k1-py/libsecp256k1/build-aux/missing
/home/oskar/secp256k1-py/libsecp256k1/build-aux/test-driver
/home/oskar/secp256k1-py/libsecp256k1/build-aux/m4/ax_jni_include_dir.m4
/home/oskar/secp256k1-py/libsecp256k1/build-aux/m4/ax_prog_cc_for_build.m4
/home/oskar/secp256k1-py/libsecp256k1/build-aux/m4/bitcoin_secp.m4
/home/oskar/secp256k1-py/libsecp256k1/build-aux/m4/libtool.m4
/home/oskar/secp256k1-py/libsecp256k1/build-aux/m4/ltoptions.m4
/home/oskar/secp256k1-py/libsecp256k1/build-aux/m4/ltsugar.m4
secp256k1new.egg-info/PKG-INFO
secp256k1new.egg-info/SOURCES.txt
secp256k1new.egg-info/dependency_links.txt
secp256k1new.egg-info/not-zip-safe
secp256k1new.egg-info/requires.txt
secp256k1new.egg-info/top_level.txt