Metadata-Version: 1.1
Name: secp256k1new
Version: 0.13.2
Summary: FFI bindings to libsecp256k1
Home-page: https://github.com/ludbb/secp256k1-py
Author: Ludvig Broberg
Author-email: lud@tutanota.com
License: MIT
Platform: UNKNOWN
Classifier: Intended Audience :: Developers
Classifier: License :: OSI Approved :: MIT License
Classifier: Programming Language :: Python :: 2
Classifier: Programming Language :: Python :: 3
Classifier: Programming Language :: Python :: Implementation :: CPython
Classifier: Programming Language :: Python :: Implementation :: PyPy
Classifier: Topic :: Software Development :: Libraries
Classifier: Topic :: Security :: Cryptography
